pySPM/__init__.py
pySPM/__main__.py
pySPM/_version.py
pySPM/align.py
pySPM/Block.py
pySPM/Bruker.py
pySPM/collection.py
pySPM/data/elements.db
pySPM/ITA.py
pySPM/ITAslicer.py
pySPM/ITAX.py
pySPM/ITM.py
pySPM/ITS.py
pySPM/mplwidget.py
pySPM/nanoscan.py
pySPM/PCA.py
pySPM/slicer.py
pySPM/SPM.py
pySPM/SXM.py
pySPM/ToF.py
pySPM/tools/__init__.py
pySPM/tools/emission_current_plotter.py
pySPM/tools/fpanel.py
pySPM/tools/mplwidget.py
pySPM/tools/spectra.py
pySPM/tools/spectraviewer.py
pySPM/tools/spectraviewer.ui
pySPM/tools/stability.py
pySPM/tools/timer_display.py
pySPM/tools/timer_display.ui
pySPM/tools/tof_timer.py
pySPM/tools/values_display.py
pySPM/tools/win32_helper.py
pySPM/utils/__init__.py
pySPM/utils/colors.py
pySPM/utils/constants.py
pySPM/utils/elts.py
pySPM/utils/fit.py
pySPM/utils/geometry.py
pySPM/utils/haar.py
pySPM/utils/math.py
pySPM/utils/misc.py
pySPM/utils/plot.py
pySPM/utils/progressbar.py
pySPM/utils/restoration.py
pySPM/utils/save.py
pySPM/utils/spectra.py
pySPM/utils/units.py
pyspm-0.6.3.dist-info/LICENSE
pyspm-0.6.3.dist-info/METADATA
pyspm-0.6.3.dist-info/WHEEL
pyspm-0.6.3.dist-info/RECORD
