Metadata-Version: 2.3
Name: pyspm
Version: 0.6.3
Summary: Library to handle SPM and ToF-SIMS data
License: Apache-2.0
Keywords: ToF,SIMS,ION-ToF,SPM,SFM,SXM,AFM,KPFM,PCA,ITA,imaging,ITM,Bruker,Nanonis
Author: Olivier Scholder
Author-email: o.scholder@gmail.com
Maintainer: Dinesh Pinto
Maintainer-email: annual.fallout_0z@icloud.com
Requires-Python: >=3.10,<3.13
Classifier: License :: OSI Approved :: Apache Software License
Classifier: Programming Language :: Python :: 3
Classifier: Programming Language :: Python :: 3.10
Classifier: Programming Language :: Python :: 3.11
Classifier: Programming Language :: Python :: 3.12
Requires-Dist: ipython (>=8.16.0,<9.0.0)
Requires-Dist: matplotlib (>=3.7.1,<4.0.0)
Requires-Dist: numpy (>=2.0.0,<3.0.0)
Requires-Dist: psutil (>=5.9.4,<6.0.0)
Requires-Dist: scikit-image (>=0.21.0)
Requires-Dist: scikit-learn (>=1.2.2,<2.0.0)
Requires-Dist: seaborn (>=0.13.0,<0.14.0)
Requires-Dist: tqdm (>=4.65.0,<5.0.0)
Project-URL: Documentation, https://nbviewer.org/github/scholi/pySPM/blob/master/doc/pySPM%20Documentation.ipynb
Project-URL: Homepage, https://github.com/scholi/pySPM
Project-URL: Repository, https://github.com/scholi/pySPM
